erlang_queue_calculator/AxisToModify.py
erlang_queue_calculator/DesiredSimulationOutcome.py
erlang_queue_calculator/InputParameter.py
erlang_queue_calculator/MMCKParameters.py
erlang_queue_calculator/MMCKPerformance.py
erlang_queue_calculator/PerformanceCharacteristics.py
erlang_queue_calculator/Result.py
erlang_queue_calculator/Simulation.py
erlang_queue_calculator/SimulationParameters.py
erlang_queue_calculator/__init__.py
erlang_queue_calculator/erlang.py
erlang_queue_calculation-0.0.2.dist-info/LICENSE
erlang_queue_calculation-0.0.2.dist-info/METADATA
erlang_queue_calculation-0.0.2.dist-info/WHEEL
erlang_queue_calculation-0.0.2.dist-info/top_level.txt
erlang_queue_calculation-0.0.2.dist-info/RECORD
