Metadata-Version: 2.1
Name: erlang_queue_calculation
Version: 0.0.2
Summary: A library for performing calculations about queues using Erlang formulae
Author-email: Lorcan O'Neill <lorcanthrope@gmail.com>
Project-URL: Homepage, https://github.com/lorcanoneill/erlang-queue-calculator-py
Project-URL: Issues, https://github.com/lorcanoneill/erlang-queue-calculator-pyissues
Classifier: Programming Language :: Python :: 3
Classifier: License :: OSI Approved :: MIT License
Classifier: Operating System :: OS Independent
Requires-Python: >=3.9
License-File: LICENSE
